pyintesishome/__init__.py
pyintesishome/const.py
pyintesishome/exceptions.py
pyintesishome/helpers.py
pyintesishome/intesisbase.py
pyintesishome/intesisbox.py
pyintesishome/intesishome.py
pyintesishome/intesishomelocal.py
pyintesishome-1.8.5.dist-info/LICENSE
pyintesishome-1.8.5.dist-info/METADATA
pyintesishome-1.8.5.dist-info/WHEEL
pyintesishome-1.8.5.dist-info/top_level.txt
pyintesishome-1.8.5.dist-info/RECORD
